_matlab_func/extractTs.m
_utiltis/__init__.py
_utiltis/data_processers.py
_utiltis/data_recorders.py
_utiltis/model_args.py
simulinkrunner-1.0.0.dist-info/LICENSE
simulinkrunner-1.0.0.dist-info/METADATA
simulinkrunner-1.0.0.dist-info/WHEEL
simulinkrunner-1.0.0.dist-info/top_level.txt
simulinkrunner-1.0.0.dist-info/RECORD
