Metadata-Version: 2.2
Name: simulinkRunner
Version: 1.0.0
Summary: A python wrapper for running the simulink model with multiple batch
Author-email: Pacria <linechecksign@163.com>
Project-URL: Homepage, https://github.com/PACRian/SimulinkRunner
Project-URL: Issues, https://github.com/PACRian/SimulinkRunner/issues
Classifier: Programming Language :: Python :: 3
Classifier: Operating System :: OS Independent
Classifier: License :: OSI Approved :: MIT License
Requires-Python: >=3.7
License-File: LICENSE
